{
  "types": {
    "axe_head": [2, -3, 13],
    "pickaxe_head": [2, 7, -15],
    "shovel_head": [2, -3],
    "spade_head": [2, -3],
    "mining_hammer_head": [2, 16],
    "mace_head": [-3, 16, 7],
    "wrench_tip": [-15, -3, -3],
    "sword_head": [2, 7, -15],
    "scraping_knife_blade": [-3, -15, -15],
    "plate": [-3, -3, -3],
    "wire_cutter_head": [],
    "bars": [13, 2, 2],
    "bars_overlay": [13, 2, 2],
    "industrial_iron_bars": [13, 2, 2],
    "support": [13, 16],
    "cleat": [7, 7, 7]
  },
  "materials": {
    "Wrought Iron": {
      "color": "#6c6c6c",
      "types": {
        "pickaxe_head": 48,
        "shovel_head": 101,
        "bars": 48
      }
    },
    "Bronze": {
      "color": "#b46a00",
      "types": {
        "axe_head": 71
      }
    },
    "Steel": {
      "color": "#4A606D",
      "types": {
        "spade_head": 85,
        "mining_hammer_head": 49,
        "support": 112,
        "plate": 100
      }
    }
  }
}